nbi/__init__.py
nbi/conf.py
nbi/forms.py
nbi/views.py
nbi/static/nbi.css
nbi/static/nbi.js
nbi/templates/nbi/area_section.html
nbi/templates/nbi/projects.html
nbi_projects_site-0.2.2.dist-info/METADATA
nbi_projects_site-0.2.2.dist-info/WHEEL
nbi_projects_site-0.2.2.dist-info/top_level.txt
nbi_projects_site-0.2.2.dist-info/RECORD
