Metadata-Version: 2.1
Name: nbi-projects-site
Version: 0.2.2
Summary: UNKNOWN
Home-page: https://github.com/rasmunk/nbi-projects-site
Author: Rasmus Munk
Author-email: rasmus.munk@nbi.ku.dk
License: UNKNOWN
Keywords: Website,Flask,MetaData
Platform: UNKNOWN
Classifier: Programming Language :: Python :: 3.5
Classifier: Programming Language :: Python :: 3.6
Classifier: Programming Language :: Python :: 3.7
Requires-Dist: flask-wtf
Requires-Dist: WTForms
Requires-Dist: projects-site
